{
  "main": {
    "id": "c7a7d28315f440b9",
    "type": "split",
    "children": [
      {
        "id": "741dc1f3ff1f157b",
        "type": "tabs",
        "children": [
          {
            "id": "1edb256743ca6b74",
            "type": "leaf",
            "state": {
              "type": "markdown",
              "state": {
                "file": "Meeting Agendas/2024-03-29.md",
                "mode": "source",
                "source": false
              }
            }
          },
          {
            "id": "adea27806f8db4cd",
            "type": "leaf",
            "state": {
              "type": "markdown",
              "state": {
                "file": "Grants/Artizen Fund.md",
                "mode": "source",
                "source": false
              }
            }
          }
        ],
        "currentTab": 1
      }
    ],
    "direction": "vertical"
  },
  "left": {
    "id": "cc66e2915c136970",
    "type": "split",
    "children": [
      {
        "id": "cf00b8a2eb812293",
        "type": "tabs",
        "children": [
          {
            "id": "d3578fdec44a5c67",
            "type": "leaf",
            "state": {
              "type": "file-explorer",
              "state": {
                "sortOrder": "alphabetical"
              }
            }
          },
          {
            "id": "e10e5654c5718d08",
            "type": "leaf",
            "state": {
              "type": "search",
              "state": {
                "query": "tag:#start-here",
                "matchingCase": false,
                "explainSearch": false,
                "collapseAll": false,
                "extraContext": false,
                "sortOrder": "alphabetical"
              }
            }
          },
          {
            "id": "322630da6ba02baf",
            "type": "leaf",
            "state": {
              "type": "bookmarks",
              "state": {}
            }
          },
          {
            "id": "0bf2762650199ae1",
            "type": "leaf",
            "state": {
              "type": "mk-file-view",
              "state": {}
            }
          },
          {
            "id": "25f431d7dcac385a",
            "type": "leaf",
            "state": {
              "type": "mk-path-view",
              "state": {}
            }
          }
        ]
      }
    ],
    "direction": "horizontal",
    "width": 300
  },
  "right": {
    "id": "d7ed3b767ac443a6",
    "type": "split",
    "children": [
      {
        "id": "b46a8cedfb3c8d9b",
        "type": "tabs",
        "children": [
          {
            "id": "2f61202ebd4b5fc0",
            "type": "leaf",
            "state": {
              "type": "backlink",
              "state": {
                "file": "Grants/Artizen Fund.md",
                "collapseAll": false,
                "extraContext": false,
                "sortOrder": "alphabetical",
                "showSearch": false,
                "searchQuery": "",
                "backlinkCollapsed": false,
                "unlinkedCollapsed": true
              }
            }
          },
          {
            "id": "511330ec4f402e45",
            "type": "leaf",
            "state": {
              "type": "outgoing-link",
              "state": {
                "file": "Grants/Artizen Fund.md",
                "linksCollapsed": false,
                "unlinkedCollapsed": true
              }
            }
          },
          {
            "id": "9835943b51c05ceb",
            "type": "leaf",
            "state": {
              "type": "tag",
              "state": {
                "sortOrder": "frequency",
                "useHierarchy": true
              }
            }
          },
          {
            "id": "dee441988e33c4b9",
            "type": "leaf",
            "state": {
              "type": "outline",
              "state": {
                "file": "Grants/Artizen Fund.md"
              }
            }
          }
        ],
        "currentTab": 3
      }
    ],
    "direction": "horizontal",
    "width": 300
  },
  "left-ribbon": {
    "hiddenItems": {
      "switcher:Open quick switcher": false,
      "graph:Open graph view": false,
      "canvas:Create new canvas": false,
      "daily-notes:Open today's daily note": false,
      "templates:Insert template": false,
      "command-palette:Open command palette": false
    }
  },
  "active": "d3578fdec44a5c67",
  "lastOpenFiles": [
    "Docs/Updates",
    "Docs/Product Guide",
    "Docs/Operations Guide",
    "Docs",
    "daoindex/Whitepaper/V0.9 Working Draft/05 Our Response_DAO Index.md",
    "Meeting Agendas/2024-03-29.md",
    "Spaces/Home",
    "Spaces",
    "Grants/Artizen Fund.md",
    "Grants/HyperDeSci Grant Discourse.md",
    "Meeting Agendas",
    "Action Plans/Action Plan for V1.0.md",
    "Questionnaire/DAO_Index_V0.9.1_XL.md",
    "Questionnaire/Untitled.canvas",
    "Action Plans/Action Plan for V0.9.md",
    "daoindex/Whitepaper/V0.9 Working Draft/08 Discussion.md",
    "Questionnaire/DAO_Index_V0.9.md",
    "Assessment Files/dao_index_assessments-11DAOs-V09-2024_03_11.csv",
    "daoindex/Whitepaper/V0.9 Working Draft/06 Methods.md",
    "daoindex/Whitepaper/V0.9 Working Draft/04 Problem Statement.md",
    "daoindex/Whitepaper/V0.9 Working Draft/09 Conclusion.md",
    "daoindex/Whitepaper/V0.9 Working Draft/01 Introduction.md",
    "daoindex/Whitepaper/V0.9 Working Draft/07 Findings.md",
    "daoindex/Whitepaper/V0.9 Working Draft/00 Table of Contents.md",
    "daoindex/Whitepaper/V0.9 Working Draft/10 Appendix.md",
    "Archive/03 Theoretical Background.md",
    "Archive/02 Contextual Background.md",
    "Archive/new note.md",
    "Archive",
    "Untitled.canvas",
    "Diagrams and Tables/Diagrams.md",
    "daoindex/Whitepaper/V0.9 Working Draft/03.1 Rationale for Questions.md",
    "Grants/Metagov Grant Application.md",
    "daoindex/Whitepaper/V0.9 Working Draft/V0.9 Working Draft.md",
    "daoindex/Whitepaper/V1.0 Working Draft/00 Table of Contents 1.md",
    "daoindex/Whitepaper/V1.0 Working Draft/10 Appendix 1.md",
    "daoindex/Whitepaper/V1.0 Working Draft",
    "daoindex/Whitepaper"
  ]
}